{"score":0,"password":"a","countAvatar":38,"money":131100,"nickName":"a","avatar":38,"userName":"a","allCards":["Alexandrite Dragon","Call of The Haunted","Call of The Haunted","Change of Heart","Change of Heart","Crab Turtle","Curtain of the dark ones","Dark magician","Exploder Dragon","Herald of Creation","Horn Imp","Magic Cylinder","Magic Jammer","Magic Jammer","Magic Jammer","Magnum Shield","Man-Eater Bug","Messenger of peace","Mind Crush","Mirage Dragon","Mirror Force","Monster Reborn","Pot of Greed","Raigeki","Scanner","Skull Guardian","Solemn Warning","Spiral Serpent","Suijin","Suijin","Supply Squad","Swords of Revealing Light","Terratiger, the Empowered Warrior","The Calculator","Torrential Tribute","Torrential Tribute","Torrential Tribute","Trap Hole","Trap Hole","Twin Twisters","Umiiruka","Vanity's Emptiness","Wall of Revealing Light","Wall of Revealing Light","Warrior Dai Grepher","Wattaildragon","Wattaildragon","Wattkid","Yami","rrr","uuu"]}